main.py
Fragpy-0.0.1.dist-info/LICENSE
Fragpy-0.0.1.dist-info/METADATA
Fragpy-0.0.1.dist-info/WHEEL
Fragpy-0.0.1.dist-info/top_level.txt
Fragpy-0.0.1.dist-info/RECORD
